pennyworth/__init__.py
pennyworth/build_jobs.py
pennyworth/command.py
pennyworth/config.py
pennyworth/driver.py
pennyworth/host.py
pennyworth/integrate.py
pennyworth/job_config.py
pennyworth/job_template.py
pennyworth/list_jobs.py
pennyworth/paths.py
pennyworth/plugin.py
pennyworth/sync.py
pennyworth/validate.py
pennyworth-0.1.0a0.dist-info/DESCRIPTION.rst
pennyworth-0.1.0a0.dist-info/METADATA
pennyworth-0.1.0a0.dist-info/RECORD
pennyworth-0.1.0a0.dist-info/WHEEL
pennyworth-0.1.0a0.dist-info/entry_points.txt
pennyworth-0.1.0a0.dist-info/metadata.json
pennyworth-0.1.0a0.dist-info/top_level.txt
