Metadata-Version: 2.0
Name: pennyworth
Version: 0.1.0a0
Summary: Manage Jenkins build configurations
Home-page: UNKNOWN
Author: Stephen Newell
Author-email: UNKNOWN
License: BSD-2
Platform: UNKNOWN
Classifier: Development Status :: 2 - Pre-Alpha
Classifier: Environment :: Console
Classifier: Intended Audience :: Developers
Classifier: License :: OSI Approved :: BSD License
Classifier: Topic :: Software Development
Classifier: Topic :: Utilities
Requires-Dist: jenkinsapi (==0.3.6)
